sndslib/__init__.py
sndslib/__main__.py
sndslib/__version__.py
sndslib/cli.py
sndslib/exceptions.py
sndslib/sndslib.py
sndslib-0.1.4.dist-info/entry_points.txt
sndslib-0.1.4.dist-info/WHEEL
sndslib-0.1.4.dist-info/METADATA
sndslib-0.1.4.dist-info/RECORD
