Metadata-Version: 2.1
Name: sndslib
Version: 0.1.4
Summary: Process and verify data from SNDS easily
Home-page: https://github.com/undersfx/sndslib
Author: undersfx
Author-email: undersoft.corp@gmail.com
Requires-Python: >=3.7,<4.0
Classifier: Programming Language :: Python :: 3
Classifier: Programming Language :: Python :: 3.10
Classifier: Programming Language :: Python :: 3.7
Classifier: Programming Language :: Python :: 3.8
Classifier: Programming Language :: Python :: 3.9
